sharik/__init__.py
sharik/abstract.py
sharik/builder.py
sharik/cli.py
sharik/data_sources.py
sharik/globs.py
sharik/tests/__init__.py
sharik/tests/test_sanity.py
sharik-0.4.1.dist-info/LICENSE
sharik-0.4.1.dist-info/METADATA
sharik-0.4.1.dist-info/WHEEL
sharik-0.4.1.dist-info/entry_points.txt
sharik-0.4.1.dist-info/top_level.txt
sharik-0.4.1.dist-info/RECORD
