Metadata-Version: 2.1
Name: sharik
Version: 0.4.1
Summary: A shar(1)-like utility with a programmatic fine-tuned API
Home-page: https://github.com/uri-yanover/sharik
Author: Uri Yanover
Author-email: throwaway+sharik@yanover.name
License: UNKNOWN
Platform: UNKNOWN
Requires-Dist: click
Requires-Dist: pydantic
Requires-Dist: dataclasses ; python_version <= "3.6"
